py2cr/__init__.py
py2cr/errors.py
py2cr/formatter.py
py2cr/numpy.py
py2cr/pycopy.py
py2cr/pymain.py
py2cr/pyos.py
py2cr/pysix.py
py2cr/pysys.py
py2cr/translator.py
py2cr/types.py
py2cr-0.1.0.dist-info/LICENSE
py2cr-0.1.0.dist-info/METADATA
py2cr-0.1.0.dist-info/WHEEL
py2cr-0.1.0.dist-info/entry_points.txt
py2cr-0.1.0.dist-info/top_level.txt
py2cr-0.1.0.dist-info/RECORD
