Metadata-Version: 2.1
Name: py2cr
Version: 0.1.0
Summary: A code translator using AST from Python to Crystal
Home-page: https://github.com/nanobowers/py2cr
Author: Ben Bowers
Author-email: nanobowers@gmail.com
License: MIT
Keywords: python crystal
Platform: UNKNOWN
Classifier: Development Status :: 4 - Beta
Classifier: Intended Audience :: Developers
Classifier: Topic :: Software Development
Classifier: License :: OSI Approved :: MIT License
Classifier: Programming Language :: Python :: 3
Classifier: Programming Language :: Python :: 3.6
Classifier: Programming Language :: Python :: 3.7
Classifier: Programming Language :: Python :: 3.8
Requires-Dist: numpy
Requires-Dist: pyyaml
